bootplot/__init__.py
bootplot/__version__.py
bootplot/base.py
bootplot/image_features.py
bootplot/sorting.py
bootplot/backend/__init__.py
bootplot/backend/base.py
bootplot/backend/matplotlib.py
test/__init__.py
test/test_bootplot.py
test/test_features.py
test/test_sorting.py
bootplot-0.0.16.dist-info/METADATA
bootplot-0.0.16.dist-info/WHEEL
bootplot-0.0.16.dist-info/top_level.txt
bootplot-0.0.16.dist-info/RECORD
