Metadata-Version: 2.4
Name: bootplot
Version: 0.0.16
Summary: bootplot is a package for black-box uncertainty visualization.
Home-page: https://github.com/davidnabergoj/bootplot
Download-URL: https://github.com/davidnabergoj/bootplot/releases
Author: David Nabergoj, Erik Štrumbelj, Bernarda Petek
Author-email: davidnabergoj4@gmail.com,
License: MIT
Project-URL: Bug Tracker, https://github.com/davidnabergoj/bootplot/issues
Keywords: bootplot,visualization,uncertainty,bootstrap
Classifier: Development Status :: 2 - Pre-Alpha
Classifier: Intended Audience :: Science/Research
Classifier: Topic :: Scientific/Engineering :: Visualization
Classifier: License :: OSI Approved :: MIT License
Classifier: Programming Language :: Python :: 3
Requires-Python: >=3.11
Requires-Dist: numpy
Requires-Dist: imageio
Requires-Dist: imageio-ffmpeg
Requires-Dist: matplotlib
Requires-Dist: tqdm
Requires-Dist: pillow
Requires-Dist: scipy
Requires-Dist: scikit-image
Requires-Dist: scikit-learn
Requires-Dist: opencv-python
Requires-Dist: networkx
Requires-Dist: pandas
Requires-Dist: jax
Dynamic: download-url
